pvclient/__init__.py
pvclient/client/__init__.py
pvclient/client/main.py
pvclient/client/purview_client.py
pvclient/utils/__init__.py
pvclient/utils/account.py
pvclient/utils/excel.py
pvclient-0.0.11.dist-info/LICENSE
pvclient-0.0.11.dist-info/METADATA
pvclient-0.0.11.dist-info/WHEEL
pvclient-0.0.11.dist-info/entry_points.txt
pvclient-0.0.11.dist-info/top_level.txt
pvclient-0.0.11.dist-info/RECORD
