Metadata-Version: 2.1
Name: pvclient
Version: 0.0.11
Summary: This package allows interacting with Azure Purview's REST API.
Home-page: https://github.com/Thanh-Truong/purview
Author: Thanh Truong
Author-email: tcthanh@gmail.com
License: MIT
Platform: UNKNOWN
Classifier: Programming Language :: Python :: 3
Classifier: License :: OSI Approved :: MIT License
Classifier: Operating System :: OS Independent
Requires-Python: >=3.6
License-File: LICENSE
Requires-Dist: pyapacheatlas (==0.6.0)
Requires-Dist: azure-identity (==1.6.0)
Requires-Dist: azure-mgmt-resource (==18.0.0)
Requires-Dist: azure-mgmt-purview (==1.0.0b1)
